pytics/__init__.py
pytics/profiler.py
pytics/visualizations.py
pytics/templates/base_template.html.j2
pytics/templates/compare_report_template.html.j2
pytics/templates/report_template.html.j2
pytics-1.1.5.dist-info/licenses/LICENSE
pytics-1.1.5.dist-info/METADATA
pytics-1.1.5.dist-info/WHEEL
pytics-1.1.5.dist-info/top_level.txt
pytics-1.1.5.dist-info/RECORD
