Metadata-Version: 2.4
Name: pytics
Version: 1.1.5
Summary: An interactive data profiling library for Python notebooks with rich HTML reports and PDF export capabilities
Author: Hans Meershoek
License: MIT
Project-URL: Homepage, https://github.com/HansMeershoek/pytics
Project-URL: Repository, https://github.com/HansMeershoek/pytics
Project-URL: Bug Tracker, https://github.com/HansMeershoek/pytics/issues
Keywords: pandas,data-analysis,profiling,visualization,jupyter
Classifier: Development Status :: 5 - Production/Stable
Classifier: Intended Audience :: Science/Research
Classifier: Intended Audience :: Developers
Classifier: License :: OSI Approved :: MIT License
Classifier: Programming Language :: Python :: 3
Classifier: Programming Language :: Python :: 3.8
Classifier: Programming Language :: Python :: 3.9
Classifier: Programming Language :: Python :: 3.10
Classifier: Programming Language :: Python :: 3.11
Classifier: Topic :: Scientific/Engineering :: Information Analysis
Classifier: Topic :: Software Development :: Libraries :: Python Modules
Classifier: Framework :: Jupyter
Requires-Python: >=3.8
License-File: LICENSE
Requires-Dist: pandas>=1.3.0
Requires-Dist: numpy>=1.20.0
Requires-Dist: plotly>=5.0.0
Requires-Dist: jinja2>=3.0.0
Requires-Dist: xhtml2pdf>=0.2.8
Requires-Dist: scipy>=1.7.0
Requires-Dist: IPython>=7.0.0
Requires-Dist: matplotlib>=3.3.0
Requires-Dist: kaleido>=0.2.1
Provides-Extra: dev
Requires-Dist: pytest>=7.0.0; extra == "dev"
Requires-Dist: black>=22.0.0; extra == "dev"
Requires-Dist: mypy>=0.900; extra == "dev"
Requires-Dist: pytest-cov>=2.0.0; extra == "dev"
Dynamic: license-file
